jrwhypy/__init__.py
jrwhypy/__version__.py
jrwhypy/data/bond.zip
jrwhypy/data.py
jrwhypy-0.1.1.dist-info/METADATA
jrwhypy-0.1.1.dist-info/WHEEL
jrwhypy-0.1.1.dist-info/RECORD
